foliant_test/__init__.py
foliant_test/config_extension.py
foliant_test/preprocessor.py
foliantcontrib.test_framework-0.1.4.dist-info/LICENSE
foliantcontrib.test_framework-0.1.4.dist-info/METADATA
foliantcontrib.test_framework-0.1.4.dist-info/WHEEL
foliantcontrib.test_framework-0.1.4.dist-info/top_level.txt
foliantcontrib.test_framework-0.1.4.dist-info/RECORD
