Metadata-Version: 2.1
Name: foliantcontrib.test_framework
Version: 0.1.4
Summary: Testing framework for Foliant
Home-page: https://github.com/foliant-docs/foliantcontrib.test_framework
Author: Daniil Minukhin
Author-email: ddddsa@gmail.com
License: MIT
Platform: any
Classifier: Development Status :: 5 - Production/Stable
Classifier: Environment :: Console
Classifier: Intended Audience :: Developers
Classifier: License :: OSI Approved :: MIT License
Classifier: Operating System :: OS Independent
Classifier: Programming Language :: Python
Classifier: Topic :: Documentation
Classifier: Topic :: Utilities
License-File: LICENSE
